[
[{"ь":3834999}]
,[{},[["мц","статься"],["мш","статься"],["мы","статься"]]]
,[{"я":3835001}]
,[{"с":3835002},[["мц","стать"],["мш","стать"],["мы","стать"]]]
,[{"е":3834989,"й":3834992,"м":3834998,"с":3835000,"х":3835003},[["ко","стать"]]]
,[{},[["мк","статься"]]]
,[{"я":3835005}]
,[{"с":3835006},[["мк","стать"]]]
,[{"ю":3835007}]
,[{"а":3834966,"е":3834986,"и":3835004,"у":3835008}]
,[{},[["аж","став"],["ай","став"]]]
,[{},[["кл","ставиться"]]]
,[{"я":3835011}]
,[{},[["км","ставиться"]]]
,[{"ь":3835013}]
,[{"с":3835014},[["км","ставить"]]]
,[{"е":3835015}]
,[{"с":3835012,"т":3835016},[["кл","ставить"]]]
,[{},[["кн","ставиться"]]]
,[{"ь":3835018}]
,[{},[["кж","ставиться"]]]
,[{"я":3835020}]
,[{"с":3835021},[["кж","ставить"]]]
,[{},[["лз","ставиться"]]]
,[{"я":3835023}]
,[{"с":3835024},[["лз","ставить"]]]
,[{"я":3835025}]
,[{},[["лб","ставиться"],["лг","ставиться"],["лп","ставиться"]]]
,[{"я":3835027}]
,[{"с":3835028},[["лб","ставить"],["лг","ставить"],["лп","ставить"]]]
,[{"о":3835029}]
,[{},[["ло","ставиться"],["лс","ставиться"]]]
,[{"я":3835031}]
,[{"с":3835032},[["ло","ставить"],["лс","ставить"]]]
,[{},[["ли","ставиться"],["лй","ставиться"],["лл","ставиться"],["лм","ставиться"]]]
,[{"я":3835034}]
,[{"с":3835035},[["ли","ставить"],["лй","ставить"],["лл","ставить"],["лм","ставить"]]]
,[{},[["ле","ставиться"],["лу","ставиться"]]]
,[{"я":3835037}]
,[{},[["лв","ставиться"],["лр","ставиться"]]]
,[{"я":3835039}]
,[{"с":3835040},[["лв","ставить"],["лр","ставить"]]]
,[{"с":3835038,"у":3835041},[["ле","ставить"],["лу","ставить"]]]
,[{},[["лл","ставиться"]]]
,[{"я":3835043}]
,[{"с":3835044},[["лл","ставить"]]]
,[{"г":3835030,"е":3835033,"й":3835036,"м":3835042,"ю":3835045}]
,[{},[["лх","ставиться"],["Лй","ставиться"]]]
,[{"я":3835047}]
,[{"с":3835048},[["лх","ставить"],["Лй","ставить"]]]
,[{},[["ла","ставиться"],["Ла","ставиться"]]]
,[{"я":3835050}]
,[{"с":3835051},[["ла","ставить"],["Ла","ставить"]]]
,[{},[["лщ","ставиться"]]]
,[{"я":3835053}]
,[{"с":3835054},[["лщ","ставить"]]]
,[{},[["лд","ставиться"],["лт","ставиться"],["лч","ставиться"]]]
,[{"я":3835056}]
,[{"и":3835055,"с":3835057},[["лд","ставить"],["лт","ставить"],["лч","ставить"]]]
,[{},[["лц","ставиться"],["лш","ставиться"],["лы","ставиться"]]]
,[{"я":3835059}]
,[{"с":3835060},[["лц","ставить"],["лш","ставить"],["лы","ставить"]]]
,[{"е":3835049,"й":3835052,"м":3835058,"х":3835061}]
,[{},[["лк","ставиться"]]]
,[{"я":3835063}]
,[{"с":3835064},[["лк","ставить"]]]
,[{"ю":3835065}]
,[{"а":3835026,"е":3835046,"и":3835062,"у":3835066}]
,[{"с":3835019,"т":3835022,"щ":3835067},[["кн","ставить"]]]
,[{"а":3833911,"е":3833966,"и":3834061,"к":3834085,"л":3834153,"н":3834193,"о":3834197,"р":3834930,"с":3834948,"у":3834949,"ц":3834962,"ш":3835009,"ы":3835010,"ь":3835017,"я":3835068},[["аа","став"],["аг","став"],["ко","стать"]]]
,[{},[["ак","стагирит"]]]
,[{"и":3835070},[["аи","стагирит"]]]
,[{},[["ал","стагирит"]]]
,[{"м":3835071,"х":3835072},[["аб","стагирит"]]]
,[{},[["ае","стагирит"]]]
,[{},[["аз","стагирит"]]]
,[{},[["ад","стагирит"]]]
,[{"в":3835075,"м":3835076}]
,[{},[["ав","стагирит"]]]
,[{},[["аж","стагирит"],["ай","стагирит"]]]
,[{"а":3835073,"е":3835074,"о":3835077,"у":3835078,"ы":3835079},[["аа","стагирит"],["аг","стагирит"]]]
,[{"т":3835080}]
,[{"и":3835081}]
,[{"р":3835082}]
,[{},[["гд","стагнация"]]]
,[{},[["гд","стагнация"]]]
,[{"й":3835084,"ю":3835085}]
,[{},[["гб","стагнация"],["гв","стагнация"],["ге","стагнация"],["гж","стагнация"],["гй","стагнация"]]]
,[{},[["гз","стагнация"]]]
,[{},[["йш","стагнационный"]]]
,[{"н":3835089}]
,[{},[["йж","стагнационный"]]]
,[{"я":3835091},[["йщ","стагнационный"]]]
,[{},[["йю","стагнационный"],["йъ","стагнационный"]]]
,[{},[["йю","стагнационный"],["йъ","стагнационный"]]]
,[{"е":3835093,"й":3835094}]
,[{},[["йб","стагнационный"],["йг","стагнационный"],["йн","стагнационный"]]]
,[{"о":3835096}]
,[{},[["йм","стагнационный"],["йп","стагнационный"]]]
,[{},[["йз","стагнационный"],["йи","стагнационный"],["йк","стагнационный"],["йл","стагнационный"]]]
,[{},[["йв","стагнационный"],["йо","стагнационный"]]]
,[{"у":3835100},[["йе","стагнационный"],["йс","стагнационный"]]]
,[{},[["йк","стагнационный"]]]
,[{"г":3835097,"е":3835098,"й":3835099,"м":3835101,"ю":3835102},[["йы","стагнационный"]]]
,[{},[["йй","стагнационный"]]]
,[{"ю":3835104}]
,[{},[["йт","стагнационный"],["Рь","стагнационный"]]]
,[{},[["йа","стагнационный"],["Рщ","стагнационный"]]]
,[{},[["йц","стагнационный"]]]
,[{"и":3835108},[["йд","стагнационный"],["йр","стагнационный"],["йф","стагнационный"]]]
,[{},[["йу","стагнационный"],["йх","стагнационный"],["йч","стагнационный"]]]
,[{"е":3835106,"й":3835107,"м":3835109,"х":3835110},[["йэ","стагнационный"]]]
,[{"а":3835092,"е":3835095,"о":3835103,"у":3835105,"ы":3835111}]
,[{"е":3835090,"н":3835112}]
,[{"н":3835113}]
,[{},[["гг","стагнация"]]]
,[{},[["гк","стагнация"]]]
,[{"и":3835116},[["ги","стагнация"]]]
,[{},[["гл","стагнация"]]]
,[{"м":3835117,"х":3835118},[["га","стагнация"]]]
,[{"е":3835086,"и":3835087,"й":3835088,"о":3835114,"ю":3835115,"я":3835119}]
,[{"и":3835120}]
,[{"ц":3835121}]
,[{"а":3835122}]
,[{},[["гд","стагфляция"]]]
,[{},[["гд","стагфляция"]]]
,[{"й":3835124,"ю":3835125}]
,[{},[["гб","стагфляция"],["гв","стагфляция"],["ге","стагфляция"],["гж","стагфляция"],["гй","стагфляция"]]]
,[{},[["гз","стагфляция"]]]
,[{},[["гг","стагфляция"]]]
,[{},[["гк","стагфляция"]]]
,[{"и":3835130},[["ги","стагфляция"]]]
,[{},[["гл","стагфляция"]]]
,[{"м":3835131,"х":3835132},[["га","стагфляция"]]]
,[{"е":3835126,"и":3835127,"й":3835128,"ю":3835129,"я":3835133}]
,[{"и":3835134}]
,[{"ц":3835135}]
,[{"я":3835136}]
,[{"л":3835137}]
,[{"и":3835083,"н":3835123,"ф":3835138}]
,[{},[["ек","стадо"]]]
,[{"и":3835140},[["еи","стадо"]]]
,[{},[["ел","стадо"]]]
,[{"м":3835141,"х":3835142},[["еб","стадо"],["еж","стадо"],["ей","стадо"]]]
,[{},[["йш","стадный"]]]
,[{"н":3835144},[["ее","стадо"]]]
,[{},[["ак","стадиал"]]]
,[{"и":3835146},[["аи","стадиал"]]]
,[{},[["ал","стадиал"]]]
,[{"м":3835147,"х":3835148},[["аб","стадиал"]]]
,[{},[["йш","стадиальный"]]]
,[{"н":3835150},[["ае","стадиал"]]]
,[{},[["аз","стадиал"]]]
,[{},[["ад","стадиал"]]]
,[{"в":3835152,"м":3835153}]
,[{},[["ав","стадиал"]]]
,[{},[["аж","стадиал"],["ай","стадиал"]]]
,[{},[["йж","стадиальный"]]]
,[{"я":3835157},[["йщ","стадиальный"]]]
,[{},[["йю","стадиальный"],["йъ","стадиальный"]]]
,[{},[["йю","стадиальный"],["йъ","стадиальный"]]]
,[{"е":3835159,"й":3835160}]
,[{},[["йб","стадиальный"],["йг","стадиальный"],["йн","стадиальный"]]]
,[{"о":3835162}]
,[{},[["йм","стадиальный"],["йп","стадиальный"]]]
,[{},[["йз","стадиальный"],["йи","стадиальный"],["йк","стадиальный"],["йл","стадиальный"]]]
,[{},[["йв","стадиальный"],["йо","стадиальный"]]]
,[{"у":3835166},[["йе","стадиальный"],["йс","стадиальный"]]]
,[{},[["гз","стадиальность"]]]
,[{"й":3835168}]
,[{},[["гб","стадиальность"],["гв","стадиальность"],["ге","стадиальность"],["гж","стадиальность"],["гй","стадиальность"]]]
,[{},[["гд","стадиальность"]]]
,[{"ю":3835171},[["га","стадиальность"],["гг","стадиальность"]]]
,[{},[["гк","стадиальность"]]]
,[{"и":3835173},[["ги","стадиальность"]]]
,[{},[["гл","стадиальность"]]]
,[{"м":3835174,"х":3835175}]
,[{"е":3835169,"и":3835170,"ь":3835172,"я":3835176}]
,[{"т":3835177}]
,[{},[["йк","стадиальный"]]]
,[{"г":3835163,"е":3835164,"й":3835165,"м":3835167,"с":3835178,"ю":3835179},[["йы","стадиальный"]]]
,[{},[["йй","стадиальный"]]]
,[{"ю":3835181}]
,[{},[["йт","стадиальный"],["Рь","стадиальный"]]]
,[{},[["йа","стадиальный"],["Рщ","стадиальный"]]]
,[{},[["йц","стадиальный"]]]
,[{"и":3835185},[["йд","стадиальный"],["йр","стадиальный"],["йф","стадиальный"]]]
,[{},[["йу","стадиальный"],["йх","стадиальный"],["йч","стадиальный"]]]
,[{"е":3835183,"й":3835184,"м":3835186,"х":3835187},[["йэ","стадиальный"]]]
,[{"а":3835158,"е":3835161,"о":3835180,"у":3835182,"ы":3835188}]
,[{"н":3835189}]
,[{"а":3835149,"е":3835151,"о":3835154,"у":3835155,"ы":3835156,"ь":3835190},[["аа","стадиал"],["аг","стадиал"]]]
,[{"л":3835191}]
,[{},[["аз","стадий"]]]
,[{},[["гд","стадия"]]]
,[{},[["ад","стадий"]]]
,[{},[["йш","стадийный"]]]
,[{},[["гд","стадия"]]]
,[{"в":3835193,"й":3835194,"м":3835195,"н":3835196,"ю":3835197}]
,[{},[["ае","стадий"],["аж","стадий"],["ай","стадий"],["гб","стадия"],["гв","стадия"],["ге","стадия"],["гж","стадия"],["гй","стадия"]]]
,[{},[["йж","стадийный"]]]
,[{"я":3835200},[["йщ","стадийный"]]]
,[{},[["йю","стадийный"],["йъ","стадийный"]]]
,[{},[["йю","стадийный"],["йъ","стадийный"]]]
,[{"е":3835202,"й":3835203}]
,[{},[["йб","стадийный"],["йг","стадийный"],["йн","стадийный"]]]
,[{"о":3835205}]
,[{},[["йм","стадийный"],["йп","стадийный"]]]
,[{},[["йз","стадийный"],["йи","стадийный"],["йк","стадийный"],["йл","стадийный"]]]
,[{},[["йв","стадийный"],["йо","стадийный"]]]
,[{"у":3835209},[["йе","стадийный"],["йс","стадийный"]]]
,[{},[["гз","стадийность"]]]
,[{"й":3835211}]
,[{},[["гб","стадийность"],["гв","стадийность"],["ге","стадийность"],["гж","стадийность"],["гй","стадийность"]]]
,[{},[["гд","стадийность"]]]
,[{"ю":3835214},[["га","стадийность"],["гг","стадийность"]]]
,[{},[["гк","стадийность"]]]
,[{"и":3835216},[["ги","стадийность"]]]
,[{},[["гл","стадийность"]]]
,[{"м":3835217,"х":3835218}]
,[{"е":3835212,"и":3835213,"ь":3835215,"я":3835219}]
,[{"т":3835220}]
,[{},[["йк","стадийный"]]]
,[{"г":3835206,"е":3835207,"й":3835208,"м":3835210,"с":3835221,"ю":3835222},[["йы","стадийный"]]]
,[{},[["йй","стадийный"]]]
,[{"ю":3835224}]
,[{},[["йт","стадийный"],["Рь","стадийный"]]]
,[{},[["йа","стадийный"],["Рщ","стадийный"]]]
,[{},[["йц","стадийный"]]]
,[{"и":3835228},[["йд","стадийный"],["йр","стадийный"],["йф","стадийный"]]]
,[{},[["йу","стадийный"],["йх","стадийный"],["йч","стадийный"]]]
,[{"е":3835226,"й":3835227,"м":3835229,"х":3835230},[["йэ","стадийный"]]]
,[{"а":3835201,"е":3835204,"о":3835223,"у":3835225,"ы":3835231}]
,[{"н":3835232},[["аа","стадий"],["аг","стадий"],["гз","стадия"]]]
,[{},[["ак","стадион"]]]
,[{"и":3835234},[["аи","стадион"]]]
,[{},[["ал","стадион"]]]
,[{"м":3835235,"х":3835236},[["аб","стадион"]]]
,[{},[["йш","стадионный"]]]
,[{"н":3835238},[["ае","стадион"]]]
,[{},[["йж","стадионный"]]]
,[{"я":3835240},[["йщ","стадионный"]]]
,[{},[["йю","стадионный"],["йъ","стадионный"]]]
,[{},[["йю","стадионный"],["йъ","стадионный"]]]
,[{"е":3835242,"й":3835243}]
,[{},[["йб","стадионный"],["йг","стадионный"],["йн","стадионный"]]]
,[{"о":3835245}]
,[{},[["йм","стадионный"],["йп","стадионный"]]]
,[{},[["йз","стадионный"],["йи","стадионный"],["йк","стадионный"],["йл","стадионный"]]]
,[{},[["йв","стадионный"],["йо","стадионный"]]]
,[{"у":3835249},[["йе","стадионный"],["йс","стадионный"]]]
,[{},[["йк","стадионный"]]]
,[{"г":3835246,"е":3835247,"й":3835248,"м":3835250,"ю":3835251},[["йы","стадионный"]]]
,[{},[["йй","стадионный"]]]
,[{"ю":3835253}]
,[{},[["йт","стадионный"],["Рь","стадионный"]]]
,[{},[["йа","стадионный"],["Рщ","стадионный"]]]
,[{},[["йц","стадионный"]]]
,[{"и":3835257},[["йд","стадионный"],["йр","стадионный"],["йф","стадионный"]]]
,[{},[["йу","стадионный"],["йх","стадионный"],["йч","стадионный"]]]
,[{"е":3835255,"й":3835256,"м":3835258,"х":3835259},[["йэ","стадионный"]]]
,[{"а":3835241,"е":3835244,"о":3835252,"у":3835254,"ы":3835260}]
,[{},[["аз","стадион"]]]
,[{},[["ад","стадион"]]]
,[{"в":3835262,"м":3835263}]
,[{},[["ав","стадион"]]]
,[{},[["аж","стадион"],["ай","стадион"]]]
,[{"а":3835237,"е":3835239,"н":3835261,"о":3835264,"у":3835265,"ы":3835266},[["аа","стадион"],["аг","стадион"]]]
,[{"н":3835267}]
,[{},[["ав","стадий"],["гг","стадия"]]]
,[{},[["ак","стадий"],["гк","стадия"]]]
,[{"и":3835270},[["аи","стадий"],["ги","стадия"]]]
,[{},[["ал","стадий"],["гл","стадия"]]]
,[{"м":3835271,"х":3835272},[["аб","стадий"],["га","стадия"]]]
,[{"а":3835192,"е":3835198,"и":3835199,"й":3835233,"о":3835268,"ю":3835269,"я":3835273}]
,[{},[["йж","стадный"]]]
,[{"я":3835275},[["йщ","стадный"]]]
,[{},[["йю","стадный"],["йъ","стадный"]]]
,[{},[["йю","стадный"],["йъ","стадный"]]]
,[{"е":3835277,"й":3835278}]
,[{},[["йб","стадный"],["йг","стадный"],["йн","стадный"]]]
,[{"о":3835280}]
,[{},[["йм","стадный"],["йп","стадный"]]]
,[{},[["йз","стадный"],["йи","стадный"],["йк","стадный"],["йл","стадный"]]]
,[{},[["йв","стадный"],["йо","стадный"]]]
,[{"у":3835284},[["йе","стадный"],["йс","стадный"]]]
,[{},[["гз","стадность"]]]
,[{"й":3835286}]
,[{},[["гб","стадность"],["гв","стадность"],["ге","стадность"],["гж","стадность"],["гй","стадность"]]]
,[{},[["гд","стадность"]]]
,[{"ю":3835289},[["га","стадность"],["гг","стадность"]]]
,[{},[["гк","стадность"]]]
,[{"и":3835291},[["ги","стадность"]]]
,[{},[["гл","стадность"]]]
,[{"м":3835292,"х":3835293}]
,[{"е":3835287,"и":3835288,"ь":3835290,"я":3835294}]
,[{"т":3835295}]
,[{},[["йк","стадный"]]]
,[{"г":3835281,"е":3835282,"й":3835283,"м":3835285,"с":3835296,"ю":3835297},[["йы","стадный"]]]
,[{},[["йй","стадный"]]]
,[{"ю":3835299}]
,[{},[["йт","стадный"],["Рь","стадный"]]]
,[{},[["йа","стадный"],["Рщ","стадный"]]]
,[{},[["йц","стадный"]]]
,[{"и":3835303},[["йд","стадный"],["йр","стадный"],["йф","стадный"]]]
,[{},[["йу","стадный"],["йх","стадный"],["йч","стадный"]]]
,[{"е":3835301,"й":3835302,"м":3835304,"х":3835305},[["йэ","стадный"]]]
,[{"а":3835276,"е":3835279,"о":3835298,"у":3835300,"ы":3835306}]
,[{},[["ед","стадо"]]]
,[{"м":3835308},[["еа","стадо"],["ег","стадо"]]]
,[{},[["ев","стадо"]]]
,[{"а":3835143,"е":3835145,"и":3835274,"н":3835307,"о":3835309,"у":3835310},[["ез","стадо"]]]
,[{},[["гд","стая"]]]
,[{},[["гз","стайка"]]]
,[{},[["нп","стаять"]]]
,[{"е":3835314}]
,[{"т":3835315},[["кр","стаять"],["нп","стаять"]]]
,[{},[["йш","стайный"]]]
,[{},[["кт","стаять"]]]
,[{"е":3835318},[["ку","стаять"]]]
,[{},[["кс","стаять"]]]
,[{"ь":3835320}]
,[{},[["гд","стая"]]]
,[{"й":3835312,"к":3835313,"м":3835316,"н":3835317,"т":3835319,"ш":3835321,"ю":3835322},[["гв","стая"],["ге","стая"]]]
,[{},[["кв","ставать"]]]
,[{},[["кд","ставать"]]]
,[{"е":3835325},[["ке","ставать"]]]
,[{},[["кг","ставать"]]]
,[{"ь":3835327}]
,[{"м":3835324,"т":3835326,"ш":3835328}]
,[{},[["ак","стаж"]]]
,[{"и":3835330},[["аи","стаж"]]]
,[{},[["ал","стаж"]]]
,[{"м":3835331,"х":3835332},[["аб","стаж"]]]
,[{},[["аз","стаж"]]]
,[{},[["ад","стаж"]]]
,[{},[["ак","стажер"]]]
,[{"и":3835336},[["аи","стажер"]]]
,[{},[["ал","стажер"]]]
,[{"м":3835337,"х":3835338},[["аб","стажер"],["аг","стажер"]]]
,[{},[["ае","стажер"]]]
,[{},[["аз","стажер"],["ай","стажер"]]]
,[{},[["ад","стажер"]]]
,[{"в":3835341,"м":3835342}]
,[{},[["ав","стажер"]]]
,[{},[["аж","стажер"]]]
,[{"а":3835339,"е":3835340,"о":3835343,"у":3835344,"ы":3835345},[["аа","стажер"]]]
,[{"й":3835334,"м":3835335,"р":3835346},[["ае","стаж"]]]
,[{},[["гк","стажёрка"]]]
,[{"и":3835348},[["ги","стажёрка"]]]
,[{},[["гл","стажёрка"]]]
,[{"м":3835349,"х":3835350},[["га","стажёрка"]]]
,[{},[["гв","стажёрка"],["ге","стажёрка"]]]
,[{},[["гб","стажёрка"],["гж","стажёрка"]]]
,[{},[["гд","стажёрка"]]]
,[{},[["гд","стажёрка"]]]
,[{"й":3835354,"ю":3835355}]
,[{},[["гг","стажёрка"]]]
,[{"а":3835351,"е":3835352,"и":3835353,"о":3835356,"у":3835357}]
,[{},[["гз","стажёрка"],["гй","стажёрка"]]]
,[{"к":3835359}]
,[{"к":3835358,"о":3835360}]
,[{"р":3835361}]
,[{},[["мз","стажироваться"]]]
,[{"я":3835363}]
,[{"с":3835364}]
,[{"я":3835365}]
,[{},[["мб","стажироваться"],["мг","стажироваться"],["мп","стажироваться"]]]
,[{"я":3835367}]
,[{"с":3835368}]
,[{"о":3835369}]
,[{},[["мо","стажироваться"],["мс","стажироваться"]]]
,[{"я":3835371}]
,[{"с":3835372}]
,[{},[["ми","стажироваться"],["мй","стажироваться"],["мл","стажироваться"],["мм","стажироваться"]]]
,[{"я":3835374}]
,[{"с":3835375}]
,[{},[["ме","стажироваться"],["му","стажироваться"]]]
,[{"я":3835377}]
,[{},[["мв","стажироваться"],["мр","стажироваться"]]]
,[{"я":3835379}]
,[{"с":3835380}]
,[{"с":3835378,"у":3835381}]
,[{},[["мл","стажироваться"]]]
,[{"я":3835383}]
,[{"с":3835384}]
,[{"г":3835370,"е":3835373,"й":3835376,"м":3835382,"ю":3835385}]
,[{},[["мх","стажироваться"],["Лк","стажироваться"]]]
,[{"я":3835387}]
,[{"с":3835388}]
,[{},[["ма","стажироваться"],["Лб","стажироваться"]]]
,[{"я":3835390}]
,[{"с":3835391}]
,[{},[["мщ","стажироваться"]]]
,[{"я":3835393}]
,[{"с":3835394}]
,[{},[["мд","стажироваться"],["мт","стажироваться"],["мч","стажироваться"]]]
,[{"я":3835396}]
,[{"и":3835395,"с":3835397}]
,[{},[["ко","стажироваться"]]]
,[{"ь":3835399}]
,[{},[["мц","стажироваться"],["мш","стажироваться"],["мы","стажироваться"]]]
,[{"я":3835401}]
,[{"с":3835402}]
,[{"е":3835389,"й":3835392,"м":3835398,"с":3835400,"х":3835403}]
,[{},[["мк","стажироваться"]]]
,[{"я":3835405}]
,[{"с":3835406}]
,[{"ю":3835407}]
,[{"а":3835366,"е":3835386,"и":3835404,"у":3835408}]
,[{"ш":3835409}]
,[{},[["ки","стажироваться"]]]
,[{"ь":3835411}]
,[{"с":3835412}]
,[{},[["кк","стажироваться"]]]
,[{"ь":3835414}]
,[{"с":3835415}]
,[{},[["кй","стажироваться"]]]
,[{"ь":3835417}]
,[{"с":3835418}]
,[{},[["кз","стажироваться"]]]
,[{"я":3835420}]
,[{"а":3835413,"и":3835416,"о":3835419,"с":3835421}]
,[{},[["ка","стажироваться"]]]
,[{"я":3835423}]
,[{"с":3835424}]
,[{"ь":3835425}]
,[{"в":3835410,"л":3835422,"т":3835426}]
,[{},[["гк","стажировка"]]]
,[{"и":3835428},[["ги","стажировка"]]]
,[{},[["гл","стажировка"]]]
,[{"м":3835429,"х":3835430},[["га","стажировка"]]]
,[{},[["гв","стажировка"],["ге","стажировка"]]]
,[{},[["гб","стажировка"],["гж","стажировка"],["гй","стажировка"]]]
,[{},[["гд","стажировка"]]]
,[{},[["гд","стажировка"]]]
,[{"й":3835434,"ю":3835435}]
,[{},[["гг","стажировка"]]]
,[{"а":3835431,"е":3835432,"и":3835433,"о":3835436,"у":3835437}]
,[{},[["гз","стажировка"]]]
,[{"к":3835439}]
,[{"а":3835427,"к":3835438,"о":3835440}]
,[{"в":3835441}]
,[{},[["кв","стажироваться"]]]
,[{"я":3835443}]
,[{"с":3835444}]
,[{},[["кд","стажироваться"]]]
,[{"ь":3835446}]
,[{"с":3835447}]
,[{},[["ке","стажироваться"]]]
,[{"я":3835449}]
,[{"е":3835448,"с":3835450}]
,[{},[["кг","стажироваться"]]]
,[{"я":3835452}]
,[{"с":3835453}]
,[{"ь":3835454}]
,[{"м":3835445,"т":3835451,"ш":3835455}]
,[{},[["кл","стажироваться"]]]
,[{"я":3835457}]
,[{},[["км","стажироваться"]]]
,[{"ь":3835459}]
,[{"с":3835460}]
,[{"е":3835461}]
,[{"с":3835458,"т":3835462}]
,[{},[["кб","стажироваться"]]]
,[{"ь":3835464}]
,[{},[["кж","стажироваться"]]]
,[{"я":3835466}]
,[{"с":3835467}]
,[{},[["лз","стажироваться"]]]
,[{"я":3835469}]
,[{"с":3835470}]
,[{"я":3835471}]
,[{},[["лб","стажироваться"],["лг","стажироваться"],["лп","стажироваться"]]]
,[{"я":3835473}]
,[{"с":3835474}]
,[{"о":3835475}]
,[{},[["ло","стажироваться"],["лс","стажироваться"]]]
,[{"я":3835477}]
,[{"с":3835478}]
,[{},[["ли","стажироваться"],["лй","стажироваться"],["лл","стажироваться"],["лм","стажироваться"]]]
,[{"я":3835480}]
,[{"с":3835481}]
,[{},[["ле","стажироваться"],["лу","стажироваться"]]]
,[{"я":3835483}]
,[{},[["лв","стажироваться"],["лр","стажироваться"]]]
,[{"я":3835485}]
,[{"с":3835486}]
,[{"с":3835484,"у":3835487}]
,[{},[["лл","стажироваться"]]]
,[{"я":3835489}]
,[{"с":3835490}]
,[{"г":3835476,"е":3835479,"й":3835482,"м":3835488,"ю":3835491}]
,[{},[["лх","стажироваться"],["Лй","стажироваться"]]]
,[{"я":3835493}]
,[{"с":3835494}]
,[{},[["ла","стажироваться"],["Ла","стажироваться"]]]
,[{"я":3835496}]
,[{"с":3835497}]
,[{},[["лщ","стажироваться"]]]
]